[{"name":"PreviewReality","description":"Manage and operate the update and preview of Ad on preview mode","endpoint":"http://localhost:8888/v1","access":{"ad":{"map":{"enable":false},"oin":{"enable":true,"tooltip":"preview the ad","path":{"template":"\\${0}","fields":["src"]}},"chart":{"enable":false}},"background":{"map":{"enable":false},"oin":{"enable":true,"tooltip":"preview the reality","path":{"template":"http://localhost:3001/b/\\${0}","fields":["_id"]}},"chart":{"enable":false}}},"storage":{"presign":"http://localhost:5000/presignedUrl"}},
{"name":"RealPixel","description":"Manage and operate the realpixel camera setup and data processing","endpoint":"http://localhost:8888/v1","access":{"analysis":{"map":{"enable":false},"oin":{"enable":false},"chart":{"enable":false}},"eye":{"map":{"enable":true,"lat":"source.geo.lat","lon":"source.geo.lon"},"oin":{"enable":true,"tooltip":"enter the eye","path":{"template":"http://localhost:8888/v1/eye/$\\${0}?cts=\\${1}","fields":["_id","_sys.created_ts"]}},"chart":{"enable":true,"xAxis":"name","yAxis":[{"field":"source.geo.lat","name":"Lat","serie":"line","type":"value","area":{}},{"field":"_sys.created_by","name":"CB","serie":"bar","type":"category"},{"field":"_sys.created_ts","name":"Time","serie":"bar","type":"time"}]}}},"storage":{"presign":"http://localhost:5000/presignedUrl"}},
{"name":"AdBoardClientScheduler","description":"Manage the Ad schedule on AdBoard","endpoint":"http://localhost:8888/v1","access":{"schedule":{"map":{"enable":false},"oin":{"enable":false},"chart":{"enable":false}}},"storage":{"presign":"http://localhost:5000/presignedUrl"}},
{"name":"Marketplace","description":"Operate and Monitor Marketplace Activities","endpoint":"http://localhost:8888/v1","access":{"ad":{"map":{"enable":false},"oin":{"enable":true,"tooltip":"preview the ad","path":{"template":"\\${0}","fields":["src"]}},"chart":{"enable":false}},"adboard":{"map":{"enable":true,"lat":"geo.lat","lon":"geo.lon"},"oin":{"enable":true,"tooltip":"preview the adboard","path":{"template":"http://localhost:3001/b/\\${0}","fields":["_id"]}},"chart":{"enable":false}},"adslot":{"map":{"enable":false},"oin":{"enable":true,"tooltip":"preview the adslot","path":{"template":"http://localhost:3001/b/\\${0}/\\${1}","fields":["adboard","ad"]}},"chart":{"enable":false}},"analysis":{"map":{"enable":false},"oin":{"enable":false},"chart":{"enable":true,"xAxis":"status","yAxis":[{"field":"type","name":"Type","serie":"bar","type":"category"}]}}},"storage":{"presign":"http://localhost:5000/presignedUrl"}}]